cs/pfx.py
cs_pfx-20250914.dist-info/WHEEL
cs_pfx-20250914.dist-info/METADATA
cs_pfx-20250914.dist-info/RECORD
